pygma/__init__.py
pygma/version.py
pygma/agents/__init__.py
pygma/agents/base_agent.py
pygma/agents/pg_agent.py
pygma/agents/tests/__init__.py
pygma/agents/tests/test_pg_agent.py
pygma-0.2.dev1.dist-info/LICENSE
pygma-0.2.dev1.dist-info/METADATA
pygma-0.2.dev1.dist-info/WHEEL
pygma-0.2.dev1.dist-info/top_level.txt
pygma-0.2.dev1.dist-info/RECORD
