Metadata-Version: 2.1
Name: pygma
Version: 0.2.dev1
Summary: Python mathematics for deep reinforcement learning on graphs
Home-page: http://github.com/abelinsky
Author: Alexander Belinsky
Author-email: a.v.belinsky@gmail.com
License: MIT
Platform: UNKNOWN
Classifier: Programming Language :: Python :: 3
Classifier: License :: OSI Approved :: MIT License
Classifier: Operating System :: OS Independent
Requires-Python: >=3.5
Requires-Dist: numpy
